tests/__init__.py
tests/conftest.py
tests/test_centerpoints.py
tests/test_distance_calc.py
tests/test_position_calc.py
tests/test_trackcenter.py
tests/test_tsection.py
trackshapeutils/__init__.py
trackshapeutils/trackshapeutils.py
trackshapeutils/tsection.dat
trackshapeutils-0.5.0b3.dist-info/licenses/LICENSE
trackshapeutils-0.5.0b3.dist-info/METADATA
trackshapeutils-0.5.0b3.dist-info/WHEEL
trackshapeutils-0.5.0b3.dist-info/top_level.txt
trackshapeutils-0.5.0b3.dist-info/RECORD
