Metadata-Version: 2.4
Name: trackshapeutils
Version: 0.5.0b3
Summary: A collection of utilities for modifying existing MSTS/ORTS track shapes.
Author: Peter Grønbæk Andersen
Author-email: Peter Grønbæk Andersen <peter@grnbk.io>
License: GNU GPL v3
Project-URL: Homepage, https://github.com/pgroenbaek/trackshape-utils
Project-URL: Issues, https://github.com/pgroenbaek/trackshape-utils/issues
Project-URL: Source, https://github.com/pgroenbaek/trackshape-utils
Classifier: Programming Language :: Python :: 3
Classifier: License :: OSI Approved :: GNU General Public License v3 or later (GPLv3+)
Classifier: Operating System :: OS Independent
Requires-Python: >=3.7
Requires-Dist: numpy
Requires-Dist: scipy
Requires-Dist: shapeio==0.5.0b3
Dynamic: author
Dynamic: requires-python
